Metadata-Version: 1.0
Name: statdistpy
Version: 1.0
Summary: Gaussian and Binomial distributions
Home-page: UNKNOWN
Author: Luiz Alberto
Author-email: gomes.luiz@gmail.com
License: UNKNOWN
Platform: UNKNOWN
